{
  "best_metric": 1.725817322731018,
  "best_model_checkpoint": "./Wiola13M\\checkpoint-20000",
  "epoch": 0.7243817854200056,
  "eval_steps": 1000,
  "global_step": 20000,
  "is_hyper_param_search": false,
  "is_local_process_zero": true,
  "is_world_process_zero": true,
  "log_history": [
    {
      "epoch": 0.001810954463550014,
      "grad_norm": 1.9558124542236328,
      "learning_rate": 1.4999999999999999e-05,
      "loss": 10.1788,
      "step": 50
    },
    {
      "epoch": 0.003621908927100028,
      "grad_norm": 1.8846240043640137,
      "learning_rate": 2.9999999999999997e-05,
      "loss": 9.5385,
      "step": 100
    },
    {
      "epoch": 0.005432863390650042,
      "grad_norm": 2.7618470191955566,
      "learning_rate": 4.4999999999999996e-05,
      "loss": 8.8473,
      "step": 150
    },
    {
      "epoch": 0.007243817854200056,
      "grad_norm": 1.985245943069458,
      "learning_rate": 5.9999999999999995e-05,
      "loss": 8.014,
      "step": 200
    },
    {
      "epoch": 0.00905477231775007,
      "grad_norm": 1.922587513923645,
      "learning_rate": 7.5e-05,
      "loss": 7.0643,
      "step": 250
    },
    {
      "epoch": 0.010865726781300085,
      "grad_norm": 2.2254414558410645,
      "learning_rate": 8.999999999999999e-05,
      "loss": 6.1745,
      "step": 300
    },
    {
      "epoch": 0.012676681244850099,
      "grad_norm": 2.030637502670288,
      "learning_rate": 0.00010499999999999999,
      "loss": 5.4491,
      "step": 350
    },
    {
      "epoch": 0.014487635708400112,
      "grad_norm": 1.9621257781982422,
      "learning_rate": 0.00011999999999999999,
      "loss": 4.8994,
      "step": 400
    },
    {
      "epoch": 0.016298590171950126,
      "grad_norm": 3.219172954559326,
      "learning_rate": 0.000135,
      "loss": 4.4903,
      "step": 450
    },
    {
      "epoch": 0.01810954463550014,
      "grad_norm": 1.6504608392715454,
      "learning_rate": 0.00015,
      "loss": 4.1788,
      "step": 500
    },
    {
      "epoch": 0.019920499099050155,
      "grad_norm": 1.9302294254302979,
      "learning_rate": 0.000165,
      "loss": 3.9337,
      "step": 550
    },
    {
      "epoch": 0.02173145356260017,
      "grad_norm": 1.7528349161148071,
      "learning_rate": 0.00017999999999999998,
      "loss": 3.757,
      "step": 600
    },
    {
      "epoch": 0.023542408026150183,
      "grad_norm": 2.5029826164245605,
      "learning_rate": 0.000195,
      "loss": 3.6147,
      "step": 650
    },
    {
      "epoch": 0.025353362489700198,
      "grad_norm": 1.7648850679397583,
      "learning_rate": 0.00020999999999999998,
      "loss": 3.5034,
      "step": 700
    },
    {
      "epoch": 0.027164316953250212,
      "grad_norm": 1.9420462846755981,
      "learning_rate": 0.000225,
      "loss": 3.3973,
      "step": 750
    },
    {
      "epoch": 0.028975271416800223,
      "grad_norm": 1.9929767847061157,
      "learning_rate": 0.00023999999999999998,
      "loss": 3.3189,
      "step": 800
    },
    {
      "epoch": 0.030786225880350238,
      "grad_norm": 1.7288830280303955,
      "learning_rate": 0.00025499999999999996,
      "loss": 3.2286,
      "step": 850
    },
    {
      "epoch": 0.03259718034390025,
      "grad_norm": 1.716060996055603,
      "learning_rate": 0.00027,
      "loss": 3.1748,
      "step": 900
    },
    {
      "epoch": 0.034408134807450266,
      "grad_norm": 1.8050830364227295,
      "learning_rate": 0.000285,
      "loss": 3.0794,
      "step": 950
    },
    {
      "epoch": 0.03621908927100028,
      "grad_norm": 1.485841155052185,
      "learning_rate": 0.0003,
      "loss": 3.0407,
      "step": 1000
    },
    {
      "epoch": 0.03621908927100028,
      "eval_loss": 3.010777473449707,
      "eval_runtime": 74.227,
      "eval_samples_per_second": 119.889,
      "eval_steps_per_second": 14.995,
      "step": 1000
    },
    {
      "epoch": 0.038030043734550295,
      "grad_norm": 1.5085238218307495,
      "learning_rate": 0.00029999487384962616,
      "loss": 2.9843,
      "step": 1050
    },
    {
      "epoch": 0.03984099819810031,
      "grad_norm": 1.2704737186431885,
      "learning_rate": 0.0002999794957488703,
      "loss": 2.9282,
      "step": 1100
    },
    {
      "epoch": 0.041651952661650324,
      "grad_norm": 1.6074286699295044,
      "learning_rate": 0.0002999538667488052,
      "loss": 2.8937,
      "step": 1150
    },
    {
      "epoch": 0.04346290712520034,
      "grad_norm": 1.1719304323196411,
      "learning_rate": 0.0002999179886011389,
      "loss": 2.8341,
      "step": 1200
    },
    {
      "epoch": 0.04527386158875035,
      "grad_norm": 1.283761978149414,
      "learning_rate": 0.0002998718637580951,
      "loss": 2.7878,
      "step": 1250
    },
    {
      "epoch": 0.04708481605230037,
      "grad_norm": 1.2685081958770752,
      "learning_rate": 0.0002998154953722457,
      "loss": 2.7572,
      "step": 1300
    },
    {
      "epoch": 0.04889577051585038,
      "grad_norm": 1.2891346216201782,
      "learning_rate": 0.0002997488872962949,
      "loss": 2.7239,
      "step": 1350
    },
    {
      "epoch": 0.050706724979400396,
      "grad_norm": 1.1495237350463867,
      "learning_rate": 0.00029967204408281613,
      "loss": 2.6978,
      "step": 1400
    },
    {
      "epoch": 0.05251767944295041,
      "grad_norm": 1.3102445602416992,
      "learning_rate": 0.0002995849709839412,
      "loss": 2.6563,
      "step": 1450
    },
    {
      "epoch": 0.054328633906500425,
      "grad_norm": 1.22013521194458,
      "learning_rate": 0.00029948767395100045,
      "loss": 2.6299,
      "step": 1500
    },
    {
      "epoch": 0.05613958837005043,
      "grad_norm": 1.1951731443405151,
      "learning_rate": 0.00029938015963411704,
      "loss": 2.6095,
      "step": 1550
    },
    {
      "epoch": 0.057950542833600446,
      "grad_norm": 1.1326366662979126,
      "learning_rate": 0.0002992624353817517,
      "loss": 2.5852,
      "step": 1600
    },
    {
      "epoch": 0.05976149729715046,
      "grad_norm": 1.1620646715164185,
      "learning_rate": 0.0002991345092402006,
      "loss": 2.5651,
      "step": 1650
    },
    {
      "epoch": 0.061572451760700475,
      "grad_norm": 1.1725059747695923,
      "learning_rate": 0.0002989963899530457,
      "loss": 2.524,
      "step": 1700
    },
    {
      "epoch": 0.0633834062242505,
      "grad_norm": 1.1720623970031738,
      "learning_rate": 0.0002988480869605567,
      "loss": 2.4986,
      "step": 1750
    },
    {
      "epoch": 0.0651943606878005,
      "grad_norm": 1.1877267360687256,
      "learning_rate": 0.00029868961039904624,
      "loss": 2.4762,
      "step": 1800
    },
    {
      "epoch": 0.06700531515135053,
      "grad_norm": 1.2609909772872925,
      "learning_rate": 0.00029852097110017676,
      "loss": 2.4646,
      "step": 1850
    },
    {
      "epoch": 0.06881626961490053,
      "grad_norm": 1.1052420139312744,
      "learning_rate": 0.00029834218059022024,
      "loss": 2.4332,
      "step": 1900
    },
    {
      "epoch": 0.07062722407845055,
      "grad_norm": 1.1520549058914185,
      "learning_rate": 0.00029815325108927063,
      "loss": 2.406,
      "step": 1950
    },
    {
      "epoch": 0.07243817854200056,
      "grad_norm": 1.1249325275421143,
      "learning_rate": 0.00029795419551040833,
      "loss": 2.4057,
      "step": 2000
    },
    {
      "epoch": 0.07243817854200056,
      "eval_loss": 2.396151065826416,
      "eval_runtime": 71.0531,
      "eval_samples_per_second": 125.244,
      "eval_steps_per_second": 15.664,
      "step": 2000
    },
    {
      "epoch": 0.07424913300555057,
      "grad_norm": 1.1151045560836792,
      "learning_rate": 0.00029774502745881775,
      "loss": 2.3653,
      "step": 2050
    },
    {
      "epoch": 0.07606008746910059,
      "grad_norm": 1.1046820878982544,
      "learning_rate": 0.00029752576123085736,
      "loss": 2.3624,
      "step": 2100
    },
    {
      "epoch": 0.0778710419326506,
      "grad_norm": 1.152419090270996,
      "learning_rate": 0.00029729641181308256,
      "loss": 2.3589,
      "step": 2150
    },
    {
      "epoch": 0.07968199639620062,
      "grad_norm": 1.1566495895385742,
      "learning_rate": 0.0002970569948812214,
      "loss": 2.3418,
      "step": 2200
    },
    {
      "epoch": 0.08149295085975063,
      "grad_norm": 1.143099308013916,
      "learning_rate": 0.00029680752679910315,
      "loss": 2.332,
      "step": 2250
    },
    {
      "epoch": 0.08330390532330065,
      "grad_norm": 1.045283555984497,
      "learning_rate": 0.0002965480246175399,
      "loss": 2.2976,
      "step": 2300
    },
    {
      "epoch": 0.08511485978685066,
      "grad_norm": 1.0436457395553589,
      "learning_rate": 0.00029627850607316094,
      "loss": 2.3058,
      "step": 2350
    },
    {
      "epoch": 0.08692581425040068,
      "grad_norm": 1.0257854461669922,
      "learning_rate": 0.0002959989895872009,
      "loss": 2.2853,
      "step": 2400
    },
    {
      "epoch": 0.08873676871395068,
      "grad_norm": 1.0158635377883911,
      "learning_rate": 0.0002957094942642401,
      "loss": 2.2691,
      "step": 2450
    },
    {
      "epoch": 0.0905477231775007,
      "grad_norm": 1.0836644172668457,
      "learning_rate": 0.0002954100398908995,
      "loss": 2.2711,
      "step": 2500
    },
    {
      "epoch": 0.09235867764105071,
      "grad_norm": 0.9993928074836731,
      "learning_rate": 0.0002951006469344877,
      "loss": 2.2491,
      "step": 2550
    },
    {
      "epoch": 0.09416963210460073,
      "grad_norm": 1.0013058185577393,
      "learning_rate": 0.0002947813365416023,
      "loss": 2.2513,
      "step": 2600
    },
    {
      "epoch": 0.09598058656815074,
      "grad_norm": 1.0081956386566162,
      "learning_rate": 0.0002944521305366844,
      "loss": 2.2347,
      "step": 2650
    },
    {
      "epoch": 0.09779154103170076,
      "grad_norm": 1.0236817598342896,
      "learning_rate": 0.0002941130514205272,
      "loss": 2.221,
      "step": 2700
    },
    {
      "epoch": 0.09960249549525077,
      "grad_norm": 0.9377487897872925,
      "learning_rate": 0.0002937641223687379,
      "loss": 2.2072,
      "step": 2750
    },
    {
      "epoch": 0.10141344995880079,
      "grad_norm": 1.0294504165649414,
      "learning_rate": 0.0002934053672301536,
      "loss": 2.1826,
      "step": 2800
    },
    {
      "epoch": 0.1032244044223508,
      "grad_norm": 0.9651481509208679,
      "learning_rate": 0.0002930368105252116,
      "loss": 2.2055,
      "step": 2850
    },
    {
      "epoch": 0.10503535888590082,
      "grad_norm": 1.0161492824554443,
      "learning_rate": 0.00029265847744427303,
      "loss": 2.1874,
      "step": 2900
    },
    {
      "epoch": 0.10684631334945083,
      "grad_norm": 0.9468438029289246,
      "learning_rate": 0.0002922703938459014,
      "loss": 2.1819,
      "step": 2950
    },
    {
      "epoch": 0.10865726781300085,
      "grad_norm": 1.02143132686615,
      "learning_rate": 0.00029187258625509513,
      "loss": 2.1621,
      "step": 3000
    },
    {
      "epoch": 0.10865726781300085,
      "eval_loss": 2.166555881500244,
      "eval_runtime": 80.358,
      "eval_samples_per_second": 110.742,
      "eval_steps_per_second": 13.851,
      "step": 3000
    },
    {
      "epoch": 0.11046822227655086,
      "grad_norm": 0.9562584161758423,
      "learning_rate": 0.00029146508186147477,
      "loss": 2.173,
      "step": 3050
    },
    {
      "epoch": 0.11227917674010086,
      "grad_norm": 0.9730893969535828,
      "learning_rate": 0.00029104790851742417,
      "loss": 2.1455,
      "step": 3100
    },
    {
      "epoch": 0.11409013120365089,
      "grad_norm": 0.9652700424194336,
      "learning_rate": 0.0002906210947361873,
      "loss": 2.1466,
      "step": 3150
    },
    {
      "epoch": 0.11590108566720089,
      "grad_norm": 0.976327657699585,
      "learning_rate": 0.0002901846696899191,
      "loss": 2.1215,
      "step": 3200
    },
    {
      "epoch": 0.11771204013075091,
      "grad_norm": 1.0150803327560425,
      "learning_rate": 0.00028973866320769183,
      "loss": 2.1378,
      "step": 3250
    },
    {
      "epoch": 0.11952299459430092,
      "grad_norm": 0.9378491640090942,
      "learning_rate": 0.00028928310577345606,
      "loss": 2.1474,
      "step": 3300
    },
    {
      "epoch": 0.12133394905785094,
      "grad_norm": 0.9610849022865295,
      "learning_rate": 0.00028881802852395727,
      "loss": 2.1185,
      "step": 3350
    },
    {
      "epoch": 0.12314490352140095,
      "grad_norm": 0.9520622491836548,
      "learning_rate": 0.0002883434632466077,
      "loss": 2.116,
      "step": 3400
    },
    {
      "epoch": 0.12495585798495097,
      "grad_norm": 0.9801678657531738,
      "learning_rate": 0.0002878594423773136,
      "loss": 2.1109,
      "step": 3450
    },
    {
      "epoch": 0.126766812448501,
      "grad_norm": 0.9089253544807434,
      "learning_rate": 0.00028736599899825856,
      "loss": 2.1075,
      "step": 3500
    },
    {
      "epoch": 0.128577766912051,
      "grad_norm": 0.9640861749649048,
      "learning_rate": 0.00028686316683564203,
      "loss": 2.1167,
      "step": 3550
    },
    {
      "epoch": 0.130388721375601,
      "grad_norm": 0.9070774912834167,
      "learning_rate": 0.00028635098025737434,
      "loss": 2.0875,
      "step": 3600
    },
    {
      "epoch": 0.13219967583915102,
      "grad_norm": 0.9039302468299866,
      "learning_rate": 0.0002858294742707278,
      "loss": 2.1028,
      "step": 3650
    },
    {
      "epoch": 0.13401063030270105,
      "grad_norm": 0.9039682149887085,
      "learning_rate": 0.00028529868451994384,
      "loss": 2.0973,
      "step": 3700
    },
    {
      "epoch": 0.13582158476625106,
      "grad_norm": 0.903252899646759,
      "learning_rate": 0.0002847586472837968,
      "loss": 2.0886,
      "step": 3750
    },
    {
      "epoch": 0.13763253922980107,
      "grad_norm": 0.93198561668396,
      "learning_rate": 0.0002842093994731145,
      "loss": 2.0763,
      "step": 3800
    },
    {
      "epoch": 0.13944349369335107,
      "grad_norm": 0.9154471755027771,
      "learning_rate": 0.00028365097862825513,
      "loss": 2.0571,
      "step": 3850
    },
    {
      "epoch": 0.1412544481569011,
      "grad_norm": 0.9285658597946167,
      "learning_rate": 0.00028308342291654174,
      "loss": 2.0695,
      "step": 3900
    },
    {
      "epoch": 0.14306540262045112,
      "grad_norm": 0.9097307324409485,
      "learning_rate": 0.00028250677112965326,
      "loss": 2.0679,
      "step": 3950
    },
    {
      "epoch": 0.14487635708400112,
      "grad_norm": 0.9798026084899902,
      "learning_rate": 0.00028192106268097334,
      "loss": 2.0595,
      "step": 4000
    },
    {
      "epoch": 0.14487635708400112,
      "eval_loss": 2.0585544109344482,
      "eval_runtime": 74.9199,
      "eval_samples_per_second": 118.78,
      "eval_steps_per_second": 14.856,
      "step": 4000
    },
    {
      "epoch": 0.14668731154755113,
      "grad_norm": 0.8909849524497986,
      "learning_rate": 0.0002813263376028964,
      "loss": 2.0359,
      "step": 4050
    },
    {
      "epoch": 0.14849826601110114,
      "grad_norm": 0.9183310866355896,
      "learning_rate": 0.00028072263654409154,
      "loss": 2.0431,
      "step": 4100
    },
    {
      "epoch": 0.15030922047465117,
      "grad_norm": 0.9399374723434448,
      "learning_rate": 0.0002801100007667243,
      "loss": 2.0463,
      "step": 4150
    },
    {
      "epoch": 0.15212017493820118,
      "grad_norm": 0.903286874294281,
      "learning_rate": 0.0002794884721436361,
      "loss": 2.0608,
      "step": 4200
    },
    {
      "epoch": 0.1539311294017512,
      "grad_norm": 0.8874121308326721,
      "learning_rate": 0.0002788580931554828,
      "loss": 2.048,
      "step": 4250
    },
    {
      "epoch": 0.1557420838653012,
      "grad_norm": 0.8731623888015747,
      "learning_rate": 0.00027821890688783083,
      "loss": 2.0305,
      "step": 4300
    },
    {
      "epoch": 0.15755303832885123,
      "grad_norm": 0.9100512266159058,
      "learning_rate": 0.0002775709570282126,
      "loss": 2.0251,
      "step": 4350
    },
    {
      "epoch": 0.15936399279240124,
      "grad_norm": 0.8615462779998779,
      "learning_rate": 0.0002769142878631403,
      "loss": 2.0308,
      "step": 4400
    },
    {
      "epoch": 0.16117494725595125,
      "grad_norm": 0.8994707465171814,
      "learning_rate": 0.000276248944275079,
      "loss": 2.0234,
      "step": 4450
    },
    {
      "epoch": 0.16298590171950125,
      "grad_norm": 0.8918218016624451,
      "learning_rate": 0.00027557497173937923,
      "loss": 2.0202,
      "step": 4500
    },
    {
      "epoch": 0.1647968561830513,
      "grad_norm": 0.8521963357925415,
      "learning_rate": 0.0002748924163211685,
      "loss": 1.9987,
      "step": 4550
    },
    {
      "epoch": 0.1666078106466013,
      "grad_norm": 0.8901366591453552,
      "learning_rate": 0.000274201324672203,
      "loss": 1.9898,
      "step": 4600
    },
    {
      "epoch": 0.1684187651101513,
      "grad_norm": 0.8855656385421753,
      "learning_rate": 0.0002735017440276788,
      "loss": 2.0076,
      "step": 4650
    },
    {
      "epoch": 0.1702297195737013,
      "grad_norm": 0.9201762676239014,
      "learning_rate": 0.00027279372220300385,
      "loss": 2.0024,
      "step": 4700
    },
    {
      "epoch": 0.17204067403725135,
      "grad_norm": 0.9167128801345825,
      "learning_rate": 0.00027207730759052924,
      "loss": 2.0068,
      "step": 4750
    },
    {
      "epoch": 0.17385162850080135,
      "grad_norm": 0.8831927180290222,
      "learning_rate": 0.0002713525491562421,
      "loss": 2.0052,
      "step": 4800
    },
    {
      "epoch": 0.17566258296435136,
      "grad_norm": 0.8489636182785034,
      "learning_rate": 0.0002706194964364187,
      "loss": 1.994,
      "step": 4850
    },
    {
      "epoch": 0.17747353742790137,
      "grad_norm": 0.8619568943977356,
      "learning_rate": 0.00026987819953423867,
      "loss": 1.976,
      "step": 4900
    },
    {
      "epoch": 0.1792844918914514,
      "grad_norm": 0.8951890468597412,
      "learning_rate": 0.0002691287091163606,
      "loss": 1.9957,
      "step": 4950
    },
    {
      "epoch": 0.1810954463550014,
      "grad_norm": 0.8567177057266235,
      "learning_rate": 0.00026837107640945905,
      "loss": 1.9897,
      "step": 5000
    },
    {
      "epoch": 0.1810954463550014,
      "eval_loss": 1.988254427909851,
      "eval_runtime": 82.0835,
      "eval_samples_per_second": 108.414,
      "eval_steps_per_second": 13.559,
      "step": 5000
    },
    {
      "epoch": 0.18290640081855142,
      "grad_norm": 0.8978298306465149,
      "learning_rate": 0.0002676053531967229,
      "loss": 1.9903,
      "step": 5050
    },
    {
      "epoch": 0.18471735528210143,
      "grad_norm": 0.8519296050071716,
      "learning_rate": 0.0002668315918143169,
      "loss": 1.9917,
      "step": 5100
    },
    {
      "epoch": 0.18652830974565143,
      "grad_norm": 0.8768444061279297,
      "learning_rate": 0.0002660498451478034,
      "loss": 1.9802,
      "step": 5150
    },
    {
      "epoch": 0.18833926420920147,
      "grad_norm": 0.8891174793243408,
      "learning_rate": 0.00026526016662852886,
      "loss": 1.9686,
      "step": 5200
    },
    {
      "epoch": 0.19015021867275148,
      "grad_norm": 0.8502144813537598,
      "learning_rate": 0.00026446261022997097,
      "loss": 1.969,
      "step": 5250
    },
    {
      "epoch": 0.19196117313630148,
      "grad_norm": 0.915191650390625,
      "learning_rate": 0.00026365723046405023,
      "loss": 1.9779,
      "step": 5300
    },
    {
      "epoch": 0.1937721275998515,
      "grad_norm": 0.837741494178772,
      "learning_rate": 0.0002628440823774037,
      "loss": 1.9627,
      "step": 5350
    },
    {
      "epoch": 0.19558308206340153,
      "grad_norm": 0.834683358669281,
      "learning_rate": 0.0002620232215476231,
      "loss": 1.9631,
      "step": 5400
    },
    {
      "epoch": 0.19739403652695153,
      "grad_norm": 0.8450649976730347,
      "learning_rate": 0.0002611947040794556,
      "loss": 1.9875,
      "step": 5450
    },
    {
      "epoch": 0.19920499099050154,
      "grad_norm": 0.8847746253013611,
      "learning_rate": 0.0002603585866009697,
      "loss": 1.9739,
      "step": 5500
    },
    {
      "epoch": 0.20101594545405155,
      "grad_norm": 0.8222176432609558,
      "learning_rate": 0.00025951492625968443,
      "loss": 1.9554,
      "step": 5550
    },
    {
      "epoch": 0.20282689991760158,
      "grad_norm": 0.8192179799079895,
      "learning_rate": 0.00025866378071866334,
      "loss": 1.944,
      "step": 5600
    },
    {
      "epoch": 0.2046378543811516,
      "grad_norm": 0.8258629441261292,
      "learning_rate": 0.0002578052081525736,
      "loss": 1.9692,
      "step": 5650
    },
    {
      "epoch": 0.2064488088447016,
      "grad_norm": 0.8557628393173218,
      "learning_rate": 0.00025693926724370956,
      "loss": 1.9372,
      "step": 5700
    },
    {
      "epoch": 0.2082597633082516,
      "grad_norm": 0.8595483899116516,
      "learning_rate": 0.00025606601717798207,
      "loss": 1.9547,
      "step": 5750
    },
    {
      "epoch": 0.21007071777180164,
      "grad_norm": 0.8581961989402771,
      "learning_rate": 0.00025518551764087326,
      "loss": 1.9532,
      "step": 5800
    },
    {
      "epoch": 0.21188167223535165,
      "grad_norm": 0.8784525394439697,
      "learning_rate": 0.0002542978288133568,
      "loss": 1.9448,
      "step": 5850
    },
    {
      "epoch": 0.21369262669890166,
      "grad_norm": 0.8308432102203369,
      "learning_rate": 0.00025340301136778483,
      "loss": 1.9371,
      "step": 5900
    },
    {
      "epoch": 0.21550358116245166,
      "grad_norm": 0.8746259212493896,
      "learning_rate": 0.00025250112646374125,
      "loss": 1.9421,
      "step": 5950
    },
    {
      "epoch": 0.2173145356260017,
      "grad_norm": 0.8785056471824646,
      "learning_rate": 0.00025159223574386114,
      "loss": 1.9496,
      "step": 6000
    },
    {
      "epoch": 0.2173145356260017,
      "eval_loss": 1.938839077949524,
      "eval_runtime": 78.0548,
      "eval_samples_per_second": 114.01,
      "eval_steps_per_second": 14.259,
      "step": 6000
    },
    {
      "epoch": 0.2191254900895517,
      "grad_norm": 0.8218588829040527,
      "learning_rate": 0.00025067640132961795,
      "loss": 1.9284,
      "step": 6050
    },
    {
      "epoch": 0.2209364445531017,
      "grad_norm": 0.8311417102813721,
      "learning_rate": 0.0002497536858170772,
      "loss": 1.9429,
      "step": 6100
    },
    {
      "epoch": 0.22274739901665172,
      "grad_norm": 0.8159801959991455,
      "learning_rate": 0.00024882415227261864,
      "loss": 1.9366,
      "step": 6150
    },
    {
      "epoch": 0.22455835348020173,
      "grad_norm": 0.8056709170341492,
      "learning_rate": 0.00024788786422862526,
      "loss": 1.9233,
      "step": 6200
    },
    {
      "epoch": 0.22636930794375176,
      "grad_norm": 0.8340697884559631,
      "learning_rate": 0.00024694488567914106,
      "loss": 1.9221,
      "step": 6250
    },
    {
      "epoch": 0.22818026240730177,
      "grad_norm": 0.9396606087684631,
      "learning_rate": 0.00024599528107549745,
      "loss": 1.9298,
      "step": 6300
    },
    {
      "epoch": 0.22999121687085178,
      "grad_norm": 0.8583187460899353,
      "learning_rate": 0.0002450391153219076,
      "loss": 1.9318,
      "step": 6350
    },
    {
      "epoch": 0.23180217133440179,
      "grad_norm": 0.8300834894180298,
      "learning_rate": 0.00024407645377103054,
      "loss": 1.9097,
      "step": 6400
    },
    {
      "epoch": 0.23361312579795182,
      "grad_norm": 0.8470647931098938,
      "learning_rate": 0.00024310736221950466,
      "loss": 1.9159,
      "step": 6450
    },
    {
      "epoch": 0.23542408026150183,
      "grad_norm": 0.8244627714157104,
      "learning_rate": 0.00024213190690345018,
      "loss": 1.9227,
      "step": 6500
    },
    {
      "epoch": 0.23723503472505184,
      "grad_norm": 0.832831621170044,
      "learning_rate": 0.00024115015449394217,
      "loss": 1.9207,
      "step": 6550
    },
    {
      "epoch": 0.23904598918860184,
      "grad_norm": 0.8115001320838928,
      "learning_rate": 0.00024016217209245374,
      "loss": 1.9086,
      "step": 6600
    },
    {
      "epoch": 0.24085694365215188,
      "grad_norm": 0.8133646249771118,
      "learning_rate": 0.00023916802722626968,
      "loss": 1.9152,
      "step": 6650
    },
    {
      "epoch": 0.24266789811570189,
      "grad_norm": 0.8458713293075562,
      "learning_rate": 0.00023816778784387094,
      "loss": 1.9224,
      "step": 6700
    },
    {
      "epoch": 0.2444788525792519,
      "grad_norm": 0.8562402129173279,
      "learning_rate": 0.00023716152231029072,
      "loss": 1.903,
      "step": 6750
    },
    {
      "epoch": 0.2462898070428019,
      "grad_norm": 0.8477017283439636,
      "learning_rate": 0.0002361492994024415,
      "loss": 1.8903,
      "step": 6800
    },
    {
      "epoch": 0.24810076150635194,
      "grad_norm": 0.8168508410453796,
      "learning_rate": 0.00023513118830441454,
      "loss": 1.9016,
      "step": 6850
    },
    {
      "epoch": 0.24991171596990194,
      "grad_norm": 0.8392953276634216,
      "learning_rate": 0.0002341072586027509,
      "loss": 1.9022,
      "step": 6900
    },
    {
      "epoch": 0.251722670433452,
      "grad_norm": 0.8365107774734497,
      "learning_rate": 0.00023307758028168557,
      "loss": 1.9004,
      "step": 6950
    },
    {
      "epoch": 0.253533624897002,
      "grad_norm": 0.8451430797576904,
      "learning_rate": 0.00023204222371836402,
      "loss": 1.9102,
      "step": 7000
    },
    {
      "epoch": 0.253533624897002,
      "eval_loss": 1.9009430408477783,
      "eval_runtime": 72.6164,
      "eval_samples_per_second": 122.548,
      "eval_steps_per_second": 15.327,
      "step": 7000
    },
    {
      "epoch": 0.255344579360552,
      "grad_norm": 0.817131757736206,
      "learning_rate": 0.00023100125967803208,
      "loss": 1.9069,
      "step": 7050
    },
    {
      "epoch": 0.257155533824102,
      "grad_norm": 0.8199076652526855,
      "learning_rate": 0.00022995475930919905,
      "loss": 1.9042,
      "step": 7100
    },
    {
      "epoch": 0.258966488287652,
      "grad_norm": 0.8620721101760864,
      "learning_rate": 0.0002289027941387751,
      "loss": 1.8992,
      "step": 7150
    },
    {
      "epoch": 0.260777442751202,
      "grad_norm": 0.8250566124916077,
      "learning_rate": 0.00022784543606718227,
      "loss": 1.8808,
      "step": 7200
    },
    {
      "epoch": 0.262588397214752,
      "grad_norm": 0.8406727313995361,
      "learning_rate": 0.00022678275736344014,
      "loss": 1.8897,
      "step": 7250
    },
    {
      "epoch": 0.26439935167830203,
      "grad_norm": 0.8282369375228882,
      "learning_rate": 0.00022571483066022657,
      "loss": 1.8749,
      "step": 7300
    },
    {
      "epoch": 0.26621030614185204,
      "grad_norm": 0.8041176199913025,
      "learning_rate": 0.00022464172894891306,
      "loss": 1.8965,
      "step": 7350
    },
    {
      "epoch": 0.2680212606054021,
      "grad_norm": 0.8332878947257996,
      "learning_rate": 0.0002235635255745762,
      "loss": 1.8936,
      "step": 7400
    },
    {
      "epoch": 0.2698322150689521,
      "grad_norm": 0.7932090759277344,
      "learning_rate": 0.0002224802942309844,
      "loss": 1.8905,
      "step": 7450
    },
    {
      "epoch": 0.2716431695325021,
      "grad_norm": 0.7869695425033569,
      "learning_rate": 0.00022139210895556104,
      "loss": 1.8812,
      "step": 7500
    },
    {
      "epoch": 0.2734541239960521,
      "grad_norm": 0.8543705940246582,
      "learning_rate": 0.00022029904412432423,
      "loss": 1.8793,
      "step": 7550
    },
    {
      "epoch": 0.27526507845960213,
      "grad_norm": 0.8882642984390259,
      "learning_rate": 0.00021920117444680317,
      "loss": 1.8846,
      "step": 7600
    },
    {
      "epoch": 0.27707603292315214,
      "grad_norm": 0.8415370583534241,
      "learning_rate": 0.00021809857496093199,
      "loss": 1.8871,
      "step": 7650
    },
    {
      "epoch": 0.27888698738670215,
      "grad_norm": 0.8402906060218811,
      "learning_rate": 0.00021699132102792097,
      "loss": 1.8685,
      "step": 7700
    },
    {
      "epoch": 0.28069794185025215,
      "grad_norm": 0.811249852180481,
      "learning_rate": 0.00021587948832710554,
      "loss": 1.8738,
      "step": 7750
    },
    {
      "epoch": 0.2825088963138022,
      "grad_norm": 0.8135554194450378,
      "learning_rate": 0.0002147631528507739,
      "loss": 1.8618,
      "step": 7800
    },
    {
      "epoch": 0.2843198507773522,
      "grad_norm": 0.8277388215065002,
      "learning_rate": 0.00021364239089897305,
      "loss": 1.8662,
      "step": 7850
    },
    {
      "epoch": 0.28613080524090223,
      "grad_norm": 0.8336319327354431,
      "learning_rate": 0.00021251727907429355,
      "loss": 1.8729,
      "step": 7900
    },
    {
      "epoch": 0.28794175970445224,
      "grad_norm": 0.8126276135444641,
      "learning_rate": 0.00021138789427663408,
      "loss": 1.8675,
      "step": 7950
    },
    {
      "epoch": 0.28975271416800225,
      "grad_norm": 0.8380399346351624,
      "learning_rate": 0.0002102543136979454,
      "loss": 1.8708,
      "step": 8000
    },
    {
      "epoch": 0.28975271416800225,
      "eval_loss": 1.8694202899932861,
      "eval_runtime": 70.5792,
      "eval_samples_per_second": 126.085,
      "eval_steps_per_second": 15.77,
      "step": 8000
    },
    {
      "epoch": 0.29156366863155225,
      "grad_norm": 0.7860820889472961,
      "learning_rate": 0.00020911661481695426,
      "loss": 1.8737,
      "step": 8050
    },
    {
      "epoch": 0.29337462309510226,
      "grad_norm": 0.8232282996177673,
      "learning_rate": 0.0002079748753938678,
      "loss": 1.8662,
      "step": 8100
    },
    {
      "epoch": 0.29518557755865227,
      "grad_norm": 0.8317840695381165,
      "learning_rate": 0.00020682917346505914,
      "loss": 1.8648,
      "step": 8150
    },
    {
      "epoch": 0.2969965320222023,
      "grad_norm": 0.8607656359672546,
      "learning_rate": 0.0002056795873377331,
      "loss": 1.8498,
      "step": 8200
    },
    {
      "epoch": 0.29880748648575234,
      "grad_norm": 0.8160783648490906,
      "learning_rate": 0.00020452619558457446,
      "loss": 1.8615,
      "step": 8250
    },
    {
      "epoch": 0.30061844094930235,
      "grad_norm": 0.834357738494873,
      "learning_rate": 0.00020336907703837748,
      "loss": 1.8749,
      "step": 8300
    },
    {
      "epoch": 0.30242939541285235,
      "grad_norm": 0.8372212052345276,
      "learning_rate": 0.00020220831078665767,
      "loss": 1.8597,
      "step": 8350
    },
    {
      "epoch": 0.30424034987640236,
      "grad_norm": 0.857650101184845,
      "learning_rate": 0.00020104397616624645,
      "loss": 1.8438,
      "step": 8400
    },
    {
      "epoch": 0.30605130433995237,
      "grad_norm": 0.8420583009719849,
      "learning_rate": 0.0001998761527578685,
      "loss": 1.8623,
      "step": 8450
    },
    {
      "epoch": 0.3078622588035024,
      "grad_norm": 0.7853153347969055,
      "learning_rate": 0.00019870492038070252,
      "loss": 1.8525,
      "step": 8500
    },
    {
      "epoch": 0.3096732132670524,
      "grad_norm": 0.8266939520835876,
      "learning_rate": 0.00019753035908692563,
      "loss": 1.8486,
      "step": 8550
    },
    {
      "epoch": 0.3114841677306024,
      "grad_norm": 0.8073140978813171,
      "learning_rate": 0.0001963525491562421,
      "loss": 1.8438,
      "step": 8600
    },
    {
      "epoch": 0.31329512219415245,
      "grad_norm": 0.8287580013275146,
      "learning_rate": 0.00019517157109039612,
      "loss": 1.851,
      "step": 8650
    },
    {
      "epoch": 0.31510607665770246,
      "grad_norm": 0.8141276836395264,
      "learning_rate": 0.0001939875056076697,
      "loss": 1.851,
      "step": 8700
    },
    {
      "epoch": 0.31691703112125247,
      "grad_norm": 0.8077007532119751,
      "learning_rate": 0.00019280043363736579,
      "loss": 1.8485,
      "step": 8750
    },
    {
      "epoch": 0.3187279855848025,
      "grad_norm": 0.8073051571846008,
      "learning_rate": 0.00019161043631427666,
      "loss": 1.8501,
      "step": 8800
    },
    {
      "epoch": 0.3205389400483525,
      "grad_norm": 0.8558452725410461,
      "learning_rate": 0.00019041759497313867,
      "loss": 1.8422,
      "step": 8850
    },
    {
      "epoch": 0.3223498945119025,
      "grad_norm": 0.8698012232780457,
      "learning_rate": 0.00018922199114307294,
      "loss": 1.8529,
      "step": 8900
    },
    {
      "epoch": 0.3241608489754525,
      "grad_norm": 0.844201385974884,
      "learning_rate": 0.00018802370654201307,
      "loss": 1.8246,
      "step": 8950
    },
    {
      "epoch": 0.3259718034390025,
      "grad_norm": 0.8165663480758667,
      "learning_rate": 0.00018682282307111987,
      "loss": 1.8335,
      "step": 9000
    },
    {
      "epoch": 0.3259718034390025,
      "eval_loss": 1.84526789188385,
      "eval_runtime": 70.5322,
      "eval_samples_per_second": 126.169,
      "eval_steps_per_second": 15.78,
      "step": 9000
    },
    {
      "epoch": 0.3277827579025525,
      "grad_norm": 0.8363304734230042,
      "learning_rate": 0.0001856194228091833,
      "loss": 1.8291,
      "step": 9050
    },
    {
      "epoch": 0.3295937123661026,
      "grad_norm": 0.8189007043838501,
      "learning_rate": 0.00018441358800701273,
      "loss": 1.8309,
      "step": 9100
    },
    {
      "epoch": 0.3314046668296526,
      "grad_norm": 0.8127615451812744,
      "learning_rate": 0.00018320540108181514,
      "loss": 1.8288,
      "step": 9150
    },
    {
      "epoch": 0.3332156212932026,
      "grad_norm": 0.8377102613449097,
      "learning_rate": 0.00018199494461156203,
      "loss": 1.8416,
      "step": 9200
    },
    {
      "epoch": 0.3350265757567526,
      "grad_norm": 0.8268140554428101,
      "learning_rate": 0.00018078230132934512,
      "loss": 1.8301,
      "step": 9250
    },
    {
      "epoch": 0.3368375302203026,
      "grad_norm": 0.8491126894950867,
      "learning_rate": 0.000179567554117722,
      "loss": 1.8412,
      "step": 9300
    },
    {
      "epoch": 0.3386484846838526,
      "grad_norm": 0.7915735840797424,
      "learning_rate": 0.00017835078600305103,
      "loss": 1.8353,
      "step": 9350
    },
    {
      "epoch": 0.3404594391474026,
      "grad_norm": 0.8367272615432739,
      "learning_rate": 0.00017713208014981648,
      "loss": 1.824,
      "step": 9400
    },
    {
      "epoch": 0.34227039361095263,
      "grad_norm": 0.8294428586959839,
      "learning_rate": 0.00017591151985494455,
      "loss": 1.8414,
      "step": 9450
    },
    {
      "epoch": 0.3440813480745027,
      "grad_norm": 0.8642491102218628,
      "learning_rate": 0.00017468918854211007,
      "loss": 1.8291,
      "step": 9500
    },
    {
      "epoch": 0.3458923025380527,
      "grad_norm": 0.8348949551582336,
      "learning_rate": 0.00017346516975603462,
      "loss": 1.8431,
      "step": 9550
    },
    {
      "epoch": 0.3477032570016027,
      "grad_norm": 0.815359354019165,
      "learning_rate": 0.00017223954715677627,
      "loss": 1.8456,
      "step": 9600
    },
    {
      "epoch": 0.3495142114651527,
      "grad_norm": 0.8250361084938049,
      "learning_rate": 0.00017101240451401168,
      "loss": 1.8254,
      "step": 9650
    },
    {
      "epoch": 0.3513251659287027,
      "grad_norm": 0.8672676682472229,
      "learning_rate": 0.00016978382570131034,
      "loss": 1.8451,
      "step": 9700
    },
    {
      "epoch": 0.35313612039225273,
      "grad_norm": 0.843298077583313,
      "learning_rate": 0.00016855389469040217,
      "loss": 1.8421,
      "step": 9750
    },
    {
      "epoch": 0.35494707485580274,
      "grad_norm": 0.8390929102897644,
      "learning_rate": 0.00016732269554543794,
      "loss": 1.8228,
      "step": 9800
    },
    {
      "epoch": 0.35675802931935274,
      "grad_norm": 0.8562666773796082,
      "learning_rate": 0.00016609031241724374,
      "loss": 1.8282,
      "step": 9850
    },
    {
      "epoch": 0.3585689837829028,
      "grad_norm": 0.8028712272644043,
      "learning_rate": 0.00016485682953756942,
      "loss": 1.8176,
      "step": 9900
    },
    {
      "epoch": 0.3603799382464528,
      "grad_norm": 0.8353468775749207,
      "learning_rate": 0.00016362233121333122,
      "loss": 1.8153,
      "step": 9950
    },
    {
      "epoch": 0.3621908927100028,
      "grad_norm": 0.8513533473014832,
      "learning_rate": 0.00016238690182084986,
      "loss": 1.8115,
      "step": 10000
    },
    {
      "epoch": 0.3621908927100028,
      "eval_loss": 1.822080373764038,
      "eval_runtime": 74.2812,
      "eval_samples_per_second": 119.801,
      "eval_steps_per_second": 14.984,
      "step": 10000
    },
    {
      "epoch": 0.36400184717355283,
      "grad_norm": 0.8092261552810669,
      "learning_rate": 0.00016115062580008315,
      "loss": 1.8105,
      "step": 10050
    },
    {
      "epoch": 0.36581280163710284,
      "grad_norm": 0.8621499538421631,
      "learning_rate": 0.0001599135876488549,
      "loss": 1.809,
      "step": 10100
    },
    {
      "epoch": 0.36762375610065284,
      "grad_norm": 0.851091742515564,
      "learning_rate": 0.0001586758719170796,
      "loss": 1.8161,
      "step": 10150
    },
    {
      "epoch": 0.36943471056420285,
      "grad_norm": 0.8583058714866638,
      "learning_rate": 0.00015743756320098332,
      "loss": 1.8175,
      "step": 10200
    },
    {
      "epoch": 0.37124566502775286,
      "grad_norm": 0.8308399319648743,
      "learning_rate": 0.00015619874613732196,
      "loss": 1.801,
      "step": 10250
    },
    {
      "epoch": 0.37305661949130287,
      "grad_norm": 0.826836347579956,
      "learning_rate": 0.0001549595053975962,
      "loss": 1.809,
      "step": 10300
    },
    {
      "epoch": 0.37486757395485293,
      "grad_norm": 0.8346395492553711,
      "learning_rate": 0.0001537199256822645,
      "loss": 1.8047,
      "step": 10350
    },
    {
      "epoch": 0.37667852841840294,
      "grad_norm": 0.8515275716781616,
      "learning_rate": 0.00015248009171495378,
      "loss": 1.8146,
      "step": 10400
    },
    {
      "epoch": 0.37848948288195294,
      "grad_norm": 0.8527790307998657,
      "learning_rate": 0.00015124008823666873,
      "loss": 1.8087,
      "step": 10450
    },
    {
      "epoch": 0.38030043734550295,
      "grad_norm": 0.8204728364944458,
      "learning_rate": 0.00015,
      "loss": 1.814,
      "step": 10500
    },
    {
      "epoch": 0.38211139180905296,
      "grad_norm": 0.8246567845344543,
      "learning_rate": 0.00014875991176333125,
      "loss": 1.8064,
      "step": 10550
    },
    {
      "epoch": 0.38392234627260297,
      "grad_norm": 0.8267943263053894,
      "learning_rate": 0.00014751990828504622,
      "loss": 1.8126,
      "step": 10600
    },
    {
      "epoch": 0.385733300736153,
      "grad_norm": 0.8376730680465698,
      "learning_rate": 0.00014628007431773547,
      "loss": 1.8005,
      "step": 10650
    },
    {
      "epoch": 0.387544255199703,
      "grad_norm": 0.8754773139953613,
      "learning_rate": 0.00014504049460240375,
      "loss": 1.7949,
      "step": 10700
    },
    {
      "epoch": 0.38935520966325304,
      "grad_norm": 0.82535320520401,
      "learning_rate": 0.000143801253862678,
      "loss": 1.8067,
      "step": 10750
    },
    {
      "epoch": 0.39116616412680305,
      "grad_norm": 0.8512724041938782,
      "learning_rate": 0.00014256243679901663,
      "loss": 1.8081,
      "step": 10800
    },
    {
      "epoch": 0.39297711859035306,
      "grad_norm": 0.8462026119232178,
      "learning_rate": 0.0001413241280829204,
      "loss": 1.7921,
      "step": 10850
    },
    {
      "epoch": 0.39478807305390307,
      "grad_norm": 0.8363431096076965,
      "learning_rate": 0.00014008641235114508,
      "loss": 1.7981,
      "step": 10900
    },
    {
      "epoch": 0.3965990275174531,
      "grad_norm": 0.8209558129310608,
      "learning_rate": 0.00013884937419991687,
      "loss": 1.8036,
      "step": 10950
    },
    {
      "epoch": 0.3984099819810031,
      "grad_norm": 0.8092831373214722,
      "learning_rate": 0.00013761309817915014,
      "loss": 1.8065,
      "step": 11000
    },
    {
      "epoch": 0.3984099819810031,
      "eval_loss": 1.8028416633605957,
      "eval_runtime": 70.7745,
      "eval_samples_per_second": 125.737,
      "eval_steps_per_second": 15.726,
      "step": 11000
    },
    {
      "epoch": 0.4002209364445531,
      "grad_norm": 0.8368477821350098,
      "learning_rate": 0.00013637766878666876,
      "loss": 1.8256,
      "step": 11050
    },
    {
      "epoch": 0.4020318909081031,
      "grad_norm": 0.8453839421272278,
      "learning_rate": 0.00013514317046243058,
      "loss": 1.8172,
      "step": 11100
    },
    {
      "epoch": 0.4038428453716531,
      "grad_norm": 0.8659654259681702,
      "learning_rate": 0.00013390968758275626,
      "loss": 1.8029,
      "step": 11150
    },
    {
      "epoch": 0.40565379983520317,
      "grad_norm": 0.8288163542747498,
      "learning_rate": 0.00013267730445456208,
      "loss": 1.8029,
      "step": 11200
    },
    {
      "epoch": 0.4074647542987532,
      "grad_norm": 0.8815070390701294,
      "learning_rate": 0.00013144610530959784,
      "loss": 1.7881,
      "step": 11250
    },
    {
      "epoch": 0.4092757087623032,
      "grad_norm": 0.8105385899543762,
      "learning_rate": 0.00013021617429868963,
      "loss": 1.7964,
      "step": 11300
    },
    {
      "epoch": 0.4110866632258532,
      "grad_norm": 0.8238645792007446,
      "learning_rate": 0.0001289875954859883,
      "loss": 1.7947,
      "step": 11350
    },
    {
      "epoch": 0.4128976176894032,
      "grad_norm": 0.8399906158447266,
      "learning_rate": 0.00012776045284322368,
      "loss": 1.7953,
      "step": 11400
    },
    {
      "epoch": 0.4147085721529532,
      "grad_norm": 0.8424611687660217,
      "learning_rate": 0.00012653483024396533,
      "loss": 1.7844,
      "step": 11450
    },
    {
      "epoch": 0.4165195266165032,
      "grad_norm": 0.8287538290023804,
      "learning_rate": 0.00012531081145788987,
      "loss": 1.797,
      "step": 11500
    },
    {
      "epoch": 0.4183304810800532,
      "grad_norm": 0.8631538152694702,
      "learning_rate": 0.00012408848014505548,
      "loss": 1.792,
      "step": 11550
    },
    {
      "epoch": 0.4201414355436033,
      "grad_norm": 0.8392460942268372,
      "learning_rate": 0.00012286791985018355,
      "loss": 1.7668,
      "step": 11600
    },
    {
      "epoch": 0.4219523900071533,
      "grad_norm": 0.8228074908256531,
      "learning_rate": 0.00012164921399694897,
      "loss": 1.7848,
      "step": 11650
    },
    {
      "epoch": 0.4237633444707033,
      "grad_norm": 0.8390864133834839,
      "learning_rate": 0.00012043244588227796,
      "loss": 1.7935,
      "step": 11700
    },
    {
      "epoch": 0.4255742989342533,
      "grad_norm": 0.8158131241798401,
      "learning_rate": 0.00011921769867065485,
      "loss": 1.7844,
      "step": 11750
    },
    {
      "epoch": 0.4273852533978033,
      "grad_norm": 0.859763503074646,
      "learning_rate": 0.00011800505538843798,
      "loss": 1.7849,
      "step": 11800
    },
    {
      "epoch": 0.4291962078613533,
      "grad_norm": 0.8187428712844849,
      "learning_rate": 0.00011679459891818484,
      "loss": 1.7702,
      "step": 11850
    },
    {
      "epoch": 0.4310071623249033,
      "grad_norm": 0.8505325317382812,
      "learning_rate": 0.00011558641199298727,
      "loss": 1.7771,
      "step": 11900
    },
    {
      "epoch": 0.43281811678845333,
      "grad_norm": 0.8229723572731018,
      "learning_rate": 0.00011438057719081671,
      "loss": 1.787,
      "step": 11950
    },
    {
      "epoch": 0.4346290712520034,
      "grad_norm": 0.8361128568649292,
      "learning_rate": 0.00011317717692888012,
      "loss": 1.773,
      "step": 12000
    },
    {
      "epoch": 0.4346290712520034,
      "eval_loss": 1.7861040830612183,
      "eval_runtime": 70.4161,
      "eval_samples_per_second": 126.377,
      "eval_steps_per_second": 15.806,
      "step": 12000
    },
    {
      "epoch": 0.4364400257155534,
      "grad_norm": 0.8588578104972839,
      "learning_rate": 0.00011197629345798689,
      "loss": 1.7821,
      "step": 12050
    },
    {
      "epoch": 0.4382509801791034,
      "grad_norm": 0.8412420749664307,
      "learning_rate": 0.00011077800885692702,
      "loss": 1.7794,
      "step": 12100
    },
    {
      "epoch": 0.4400619346426534,
      "grad_norm": 0.8208729028701782,
      "learning_rate": 0.00010958240502686129,
      "loss": 1.767,
      "step": 12150
    },
    {
      "epoch": 0.4418728891062034,
      "grad_norm": 0.8476991653442383,
      "learning_rate": 0.00010838956368572334,
      "loss": 1.7677,
      "step": 12200
    },
    {
      "epoch": 0.44368384356975343,
      "grad_norm": 0.8186628818511963,
      "learning_rate": 0.00010719956636263423,
      "loss": 1.782,
      "step": 12250
    },
    {
      "epoch": 0.44549479803330344,
      "grad_norm": 0.8215035796165466,
      "learning_rate": 0.0001060124943923303,
      "loss": 1.759,
      "step": 12300
    },
    {
      "epoch": 0.44730575249685345,
      "grad_norm": 0.8446810245513916,
      "learning_rate": 0.00010482842890960389,
      "loss": 1.7707,
      "step": 12350
    },
    {
      "epoch": 0.44911670696040346,
      "grad_norm": 0.8577568531036377,
      "learning_rate": 0.0001036474508437579,
      "loss": 1.7668,
      "step": 12400
    },
    {
      "epoch": 0.4509276614239535,
      "grad_norm": 0.8422988653182983,
      "learning_rate": 0.00010246964091307433,
      "loss": 1.7778,
      "step": 12450
    },
    {
      "epoch": 0.4527386158875035,
      "grad_norm": 0.8196696639060974,
      "learning_rate": 0.00010129507961929748,
      "loss": 1.7742,
      "step": 12500
    },
    {
      "epoch": 0.45454957035105353,
      "grad_norm": 0.8323593735694885,
      "learning_rate": 0.00010012384724213148,
      "loss": 1.7706,
      "step": 12550
    },
    {
      "epoch": 0.45636052481460354,
      "grad_norm": 0.8478230834007263,
      "learning_rate": 9.895602383375353e-05,
      "loss": 1.7774,
      "step": 12600
    },
    {
      "epoch": 0.45817147927815355,
      "grad_norm": 0.8568398356437683,
      "learning_rate": 9.779168921334232e-05,
      "loss": 1.7851,
      "step": 12650
    },
    {
      "epoch": 0.45998243374170356,
      "grad_norm": 0.8753241896629333,
      "learning_rate": 9.663092296162251e-05,
      "loss": 1.7701,
      "step": 12700
    },
    {
      "epoch": 0.46179338820525356,
      "grad_norm": 0.8499313592910767,
      "learning_rate": 9.547380441542549e-05,
      "loss": 1.7625,
      "step": 12750
    },
    {
      "epoch": 0.46360434266880357,
      "grad_norm": 0.8426764607429504,
      "learning_rate": 9.432041266226686e-05,
      "loss": 1.7713,
      "step": 12800
    },
    {
      "epoch": 0.46541529713235363,
      "grad_norm": 0.8281407356262207,
      "learning_rate": 9.317082653494081e-05,
      "loss": 1.7765,
      "step": 12850
    },
    {
      "epoch": 0.46722625159590364,
      "grad_norm": 0.8567844033241272,
      "learning_rate": 9.202512460613219e-05,
      "loss": 1.7712,
      "step": 12900
    },
    {
      "epoch": 0.46903720605945365,
      "grad_norm": 0.8209742307662964,
      "learning_rate": 9.088338518304578e-05,
      "loss": 1.7645,
      "step": 12950
    },
    {
      "epoch": 0.47084816052300366,
      "grad_norm": 0.8566125631332397,
      "learning_rate": 8.97456863020546e-05,
      "loss": 1.7557,
      "step": 13000
    },
    {
      "epoch": 0.47084816052300366,
      "eval_loss": 1.7713803052902222,
      "eval_runtime": 70.6861,
      "eval_samples_per_second": 125.895,
      "eval_steps_per_second": 15.746,
      "step": 13000
    },
    {
      "epoch": 0.47265911498655366,
      "grad_norm": 0.871849536895752,
      "learning_rate": 8.86121057233659e-05,
      "loss": 1.7672,
      "step": 13050
    },
    {
      "epoch": 0.47447006945010367,
      "grad_norm": 0.8435642123222351,
      "learning_rate": 8.748272092570646e-05,
      "loss": 1.7644,
      "step": 13100
    },
    {
      "epoch": 0.4762810239136537,
      "grad_norm": 0.8611681461334229,
      "learning_rate": 8.635760910102695e-05,
      "loss": 1.7621,
      "step": 13150
    },
    {
      "epoch": 0.4780919783772037,
      "grad_norm": 0.8348284363746643,
      "learning_rate": 8.523684714922608e-05,
      "loss": 1.7525,
      "step": 13200
    },
    {
      "epoch": 0.4799029328407537,
      "grad_norm": 0.8699232935905457,
      "learning_rate": 8.412051167289446e-05,
      "loss": 1.7689,
      "step": 13250
    },
    {
      "epoch": 0.48171388730430376,
      "grad_norm": 0.8355242609977722,
      "learning_rate": 8.300867897207903e-05,
      "loss": 1.7693,
      "step": 13300
    },
    {
      "epoch": 0.48352484176785376,
      "grad_norm": 0.837235689163208,
      "learning_rate": 8.190142503906798e-05,
      "loss": 1.7576,
      "step": 13350
    },
    {
      "epoch": 0.48533579623140377,
      "grad_norm": 0.8228093981742859,
      "learning_rate": 8.079882555319684e-05,
      "loss": 1.7665,
      "step": 13400
    },
    {
      "epoch": 0.4871467506949538,
      "grad_norm": 0.8727956414222717,
      "learning_rate": 7.970095587567578e-05,
      "loss": 1.7746,
      "step": 13450
    },
    {
      "epoch": 0.4889577051585038,
      "grad_norm": 0.8665521144866943,
      "learning_rate": 7.860789104443896e-05,
      "loss": 1.7665,
      "step": 13500
    },
    {
      "epoch": 0.4907686596220538,
      "grad_norm": 0.8160901069641113,
      "learning_rate": 7.75197057690156e-05,
      "loss": 1.7815,
      "step": 13550
    },
    {
      "epoch": 0.4925796140856038,
      "grad_norm": 0.8181907534599304,
      "learning_rate": 7.643647442542382e-05,
      "loss": 1.7542,
      "step": 13600
    },
    {
      "epoch": 0.4943905685491538,
      "grad_norm": 0.8266783356666565,
      "learning_rate": 7.535827105108696e-05,
      "loss": 1.764,
      "step": 13650
    },
    {
      "epoch": 0.49620152301270387,
      "grad_norm": 0.8633971810340881,
      "learning_rate": 7.428516933977347e-05,
      "loss": 1.7701,
      "step": 13700
    },
    {
      "epoch": 0.4980124774762539,
      "grad_norm": 0.8653848171234131,
      "learning_rate": 7.321724263655988e-05,
      "loss": 1.7702,
      "step": 13750
    },
    {
      "epoch": 0.4998234319398039,
      "grad_norm": 0.8490447998046875,
      "learning_rate": 7.215456393281776e-05,
      "loss": 1.7624,
      "step": 13800
    },
    {
      "epoch": 0.5016343864033539,
      "grad_norm": 0.8671083450317383,
      "learning_rate": 7.10972058612249e-05,
      "loss": 1.7622,
      "step": 13850
    },
    {
      "epoch": 0.503445340866904,
      "grad_norm": 0.8671828508377075,
      "learning_rate": 7.004524069080096e-05,
      "loss": 1.7628,
      "step": 13900
    },
    {
      "epoch": 0.5052562953304539,
      "grad_norm": 0.8467494249343872,
      "learning_rate": 6.899874032196797e-05,
      "loss": 1.7464,
      "step": 13950
    },
    {
      "epoch": 0.507067249794004,
      "grad_norm": 0.8648102879524231,
      "learning_rate": 6.795777628163599e-05,
      "loss": 1.7585,
      "step": 14000
    },
    {
      "epoch": 0.507067249794004,
      "eval_loss": 1.758442759513855,
      "eval_runtime": 70.3854,
      "eval_samples_per_second": 126.432,
      "eval_steps_per_second": 15.813,
      "step": 14000
    },
    {
      "epoch": 0.5088782042575539,
      "grad_norm": 0.858515739440918,
      "learning_rate": 6.692241971831445e-05,
      "loss": 1.7475,
      "step": 14050
    },
    {
      "epoch": 0.510689158721104,
      "grad_norm": 0.8701948523521423,
      "learning_rate": 6.58927413972491e-05,
      "loss": 1.7519,
      "step": 14100
    },
    {
      "epoch": 0.5125001131846539,
      "grad_norm": 0.8434861302375793,
      "learning_rate": 6.486881169558546e-05,
      "loss": 1.7556,
      "step": 14150
    },
    {
      "epoch": 0.514311067648204,
      "grad_norm": 0.8482869267463684,
      "learning_rate": 6.385070059755846e-05,
      "loss": 1.7466,
      "step": 14200
    },
    {
      "epoch": 0.516122022111754,
      "grad_norm": 0.8727043271064758,
      "learning_rate": 6.283847768970926e-05,
      "loss": 1.7542,
      "step": 14250
    },
    {
      "epoch": 0.517932976575304,
      "grad_norm": 0.8646461963653564,
      "learning_rate": 6.183221215612904e-05,
      "loss": 1.751,
      "step": 14300
    },
    {
      "epoch": 0.5197439310388541,
      "grad_norm": 0.8618670105934143,
      "learning_rate": 6.0831972773730316e-05,
      "loss": 1.7408,
      "step": 14350
    },
    {
      "epoch": 0.521554885502404,
      "grad_norm": 0.8422278165817261,
      "learning_rate": 5.983782790754623e-05,
      "loss": 1.7619,
      "step": 14400
    },
    {
      "epoch": 0.5233658399659541,
      "grad_norm": 0.846784234046936,
      "learning_rate": 5.884984550605782e-05,
      "loss": 1.7568,
      "step": 14450
    },
    {
      "epoch": 0.525176794429504,
      "grad_norm": 0.8581988215446472,
      "learning_rate": 5.786809309654982e-05,
      "loss": 1.7422,
      "step": 14500
    },
    {
      "epoch": 0.5269877488930541,
      "grad_norm": 0.8875020742416382,
      "learning_rate": 5.6892637780495324e-05,
      "loss": 1.7393,
      "step": 14550
    },
    {
      "epoch": 0.5287987033566041,
      "grad_norm": 0.8734170794487,
      "learning_rate": 5.592354622896944e-05,
      "loss": 1.7502,
      "step": 14600
    },
    {
      "epoch": 0.5306096578201541,
      "grad_norm": 0.8504616022109985,
      "learning_rate": 5.496088467809242e-05,
      "loss": 1.7577,
      "step": 14650
    },
    {
      "epoch": 0.5324206122837041,
      "grad_norm": 0.8575912714004517,
      "learning_rate": 5.40047189245025e-05,
      "loss": 1.7532,
      "step": 14700
    },
    {
      "epoch": 0.5342315667472541,
      "grad_norm": 0.8781095743179321,
      "learning_rate": 5.305511432085884e-05,
      "loss": 1.7371,
      "step": 14750
    },
    {
      "epoch": 0.5360425212108042,
      "grad_norm": 0.8988766670227051,
      "learning_rate": 5.211213577137469e-05,
      "loss": 1.7528,
      "step": 14800
    },
    {
      "epoch": 0.5378534756743542,
      "grad_norm": 0.8444653153419495,
      "learning_rate": 5.11758477273813e-05,
      "loss": 1.7478,
      "step": 14850
    },
    {
      "epoch": 0.5396644301379042,
      "grad_norm": 0.8932321667671204,
      "learning_rate": 5.024631418292274e-05,
      "loss": 1.738,
      "step": 14900
    },
    {
      "epoch": 0.5414753846014542,
      "grad_norm": 0.8585721850395203,
      "learning_rate": 4.9323598670382096e-05,
      "loss": 1.7575,
      "step": 14950
    },
    {
      "epoch": 0.5432863390650042,
      "grad_norm": 0.8384203314781189,
      "learning_rate": 4.840776425613886e-05,
      "loss": 1.7438,
      "step": 15000
    },
    {
      "epoch": 0.5432863390650042,
      "eval_loss": 1.7471288442611694,
      "eval_runtime": 73.2239,
      "eval_samples_per_second": 121.531,
      "eval_steps_per_second": 15.2,
      "step": 15000
    },
    {
      "epoch": 0.5450972935285542,
      "grad_norm": 0.8659111857414246,
      "learning_rate": 4.749887353625874e-05,
      "loss": 1.745,
      "step": 15050
    },
    {
      "epoch": 0.5469082479921042,
      "grad_norm": 0.8637661337852478,
      "learning_rate": 4.659698863221514e-05,
      "loss": 1.7454,
      "step": 15100
    },
    {
      "epoch": 0.5487192024556542,
      "grad_norm": 0.8949984908103943,
      "learning_rate": 4.57021711866432e-05,
      "loss": 1.7479,
      "step": 15150
    },
    {
      "epoch": 0.5505301569192043,
      "grad_norm": 0.8618626594543457,
      "learning_rate": 4.481448235912671e-05,
      "loss": 1.74,
      "step": 15200
    },
    {
      "epoch": 0.5523411113827543,
      "grad_norm": 0.8490021824836731,
      "learning_rate": 4.3933982822017876e-05,
      "loss": 1.7523,
      "step": 15250
    },
    {
      "epoch": 0.5541520658463043,
      "grad_norm": 0.8670493364334106,
      "learning_rate": 4.306073275629044e-05,
      "loss": 1.7356,
      "step": 15300
    },
    {
      "epoch": 0.5559630203098543,
      "grad_norm": 0.882551908493042,
      "learning_rate": 4.219479184742642e-05,
      "loss": 1.7328,
      "step": 15350
    },
    {
      "epoch": 0.5577739747734043,
      "grad_norm": 0.8707594871520996,
      "learning_rate": 4.133621928133665e-05,
      "loss": 1.746,
      "step": 15400
    },
    {
      "epoch": 0.5595849292369544,
      "grad_norm": 0.8870259523391724,
      "learning_rate": 4.048507374031555e-05,
      "loss": 1.733,
      "step": 15450
    },
    {
      "epoch": 0.5613958837005043,
      "grad_norm": 0.8571605086326599,
      "learning_rate": 3.964141339903026e-05,
      "loss": 1.734,
      "step": 15500
    },
    {
      "epoch": 0.5632068381640544,
      "grad_norm": 0.863075315952301,
      "learning_rate": 3.8805295920544374e-05,
      "loss": 1.7565,
      "step": 15550
    },
    {
      "epoch": 0.5650177926276044,
      "grad_norm": 0.8828005790710449,
      "learning_rate": 3.797677845237696e-05,
      "loss": 1.7488,
      "step": 15600
    },
    {
      "epoch": 0.5668287470911544,
      "grad_norm": 0.8779637217521667,
      "learning_rate": 3.715591762259633e-05,
      "loss": 1.7386,
      "step": 15650
    },
    {
      "epoch": 0.5686397015547044,
      "grad_norm": 0.8669997453689575,
      "learning_rate": 3.6342769535949834e-05,
      "loss": 1.7176,
      "step": 15700
    },
    {
      "epoch": 0.5704506560182544,
      "grad_norm": 0.8688264489173889,
      "learning_rate": 3.5537389770029046e-05,
      "loss": 1.7409,
      "step": 15750
    },
    {
      "epoch": 0.5722616104818045,
      "grad_norm": 0.8775643110275269,
      "learning_rate": 3.473983337147118e-05,
      "loss": 1.7294,
      "step": 15800
    },
    {
      "epoch": 0.5740725649453544,
      "grad_norm": 0.8781272172927856,
      "learning_rate": 3.39501548521966e-05,
      "loss": 1.7303,
      "step": 15850
    },
    {
      "epoch": 0.5758835194089045,
      "grad_norm": 0.9333208203315735,
      "learning_rate": 3.316840818568315e-05,
      "loss": 1.7295,
      "step": 15900
    },
    {
      "epoch": 0.5776944738724544,
      "grad_norm": 0.8629750609397888,
      "learning_rate": 3.239464680327706e-05,
      "loss": 1.7408,
      "step": 15950
    },
    {
      "epoch": 0.5795054283360045,
      "grad_norm": 0.8728818893432617,
      "learning_rate": 3.162892359054098e-05,
      "loss": 1.7167,
      "step": 16000
    },
    {
      "epoch": 0.5795054283360045,
      "eval_loss": 1.7391303777694702,
      "eval_runtime": 70.8624,
      "eval_samples_per_second": 125.581,
      "eval_steps_per_second": 15.706,
      "step": 16000
    },
    {
      "epoch": 0.5813163827995546,
      "grad_norm": 0.8430949449539185,
      "learning_rate": 3.087129088363934e-05,
      "loss": 1.7313,
      "step": 16050
    },
    {
      "epoch": 0.5831273372631045,
      "grad_norm": 0.8456268906593323,
      "learning_rate": 3.0121800465761293e-05,
      "loss": 1.7432,
      "step": 16100
    },
    {
      "epoch": 0.5849382917266546,
      "grad_norm": 0.873253345489502,
      "learning_rate": 2.9380503563581292e-05,
      "loss": 1.726,
      "step": 16150
    },
    {
      "epoch": 0.5867492461902045,
      "grad_norm": 0.8854848146438599,
      "learning_rate": 2.8647450843757897e-05,
      "loss": 1.7302,
      "step": 16200
    },
    {
      "epoch": 0.5885602006537546,
      "grad_norm": 0.8502493500709534,
      "learning_rate": 2.792269240947076e-05,
      "loss": 1.7343,
      "step": 16250
    },
    {
      "epoch": 0.5903711551173045,
      "grad_norm": 0.8668370246887207,
      "learning_rate": 2.7206277796996144e-05,
      "loss": 1.7339,
      "step": 16300
    },
    {
      "epoch": 0.5921821095808546,
      "grad_norm": 0.8910673260688782,
      "learning_rate": 2.6498255972321135e-05,
      "loss": 1.732,
      "step": 16350
    },
    {
      "epoch": 0.5939930640444046,
      "grad_norm": 0.8552797436714172,
      "learning_rate": 2.5798675327796993e-05,
      "loss": 1.7107,
      "step": 16400
    },
    {
      "epoch": 0.5958040185079546,
      "grad_norm": 0.8521983027458191,
      "learning_rate": 2.5107583678831445e-05,
      "loss": 1.7183,
      "step": 16450
    },
    {
      "epoch": 0.5976149729715047,
      "grad_norm": 0.8963445425033569,
      "learning_rate": 2.4425028260620715e-05,
      "loss": 1.7169,
      "step": 16500
    },
    {
      "epoch": 0.5994259274350546,
      "grad_norm": 0.8720009922981262,
      "learning_rate": 2.375105572492093e-05,
      "loss": 1.7215,
      "step": 16550
    },
    {
      "epoch": 0.6012368818986047,
      "grad_norm": 0.8530541062355042,
      "learning_rate": 2.3085712136859668e-05,
      "loss": 1.7362,
      "step": 16600
    },
    {
      "epoch": 0.6030478363621546,
      "grad_norm": 0.8420068621635437,
      "learning_rate": 2.2429042971787365e-05,
      "loss": 1.7207,
      "step": 16650
    },
    {
      "epoch": 0.6048587908257047,
      "grad_norm": 0.8679628968238831,
      "learning_rate": 2.178109311216913e-05,
      "loss": 1.7395,
      "step": 16700
    },
    {
      "epoch": 0.6066697452892547,
      "grad_norm": 0.8846210837364197,
      "learning_rate": 2.1141906844517203e-05,
      "loss": 1.7304,
      "step": 16750
    },
    {
      "epoch": 0.6084806997528047,
      "grad_norm": 0.8682114481925964,
      "learning_rate": 2.0511527856363912e-05,
      "loss": 1.7398,
      "step": 16800
    },
    {
      "epoch": 0.6102916542163548,
      "grad_norm": 0.8462464809417725,
      "learning_rate": 1.9889999233275704e-05,
      "loss": 1.7256,
      "step": 16850
    },
    {
      "epoch": 0.6121026086799047,
      "grad_norm": 0.8867937922477722,
      "learning_rate": 1.927736345590839e-05,
      "loss": 1.7225,
      "step": 16900
    },
    {
      "epoch": 0.6139135631434548,
      "grad_norm": 0.8733996748924255,
      "learning_rate": 1.8673662397103577e-05,
      "loss": 1.7355,
      "step": 16950
    },
    {
      "epoch": 0.6157245176070048,
      "grad_norm": 0.8472720384597778,
      "learning_rate": 1.8078937319026654e-05,
      "loss": 1.7169,
      "step": 17000
    },
    {
      "epoch": 0.6157245176070048,
      "eval_loss": 1.7328472137451172,
      "eval_runtime": 70.5313,
      "eval_samples_per_second": 126.171,
      "eval_steps_per_second": 15.78,
      "step": 17000
    },
    {
      "epoch": 0.6175354720705548,
      "grad_norm": 0.8786899447441101,
      "learning_rate": 1.7493228870346716e-05,
      "loss": 1.7397,
      "step": 17050
    },
    {
      "epoch": 0.6193464265341048,
      "grad_norm": 0.9218168258666992,
      "learning_rate": 1.6916577083458228e-05,
      "loss": 1.7487,
      "step": 17100
    },
    {
      "epoch": 0.6211573809976548,
      "grad_norm": 0.8809800148010254,
      "learning_rate": 1.634902137174483e-05,
      "loss": 1.7255,
      "step": 17150
    },
    {
      "epoch": 0.6229683354612048,
      "grad_norm": 0.872061014175415,
      "learning_rate": 1.579060052688548e-05,
      "loss": 1.7265,
      "step": 17200
    },
    {
      "epoch": 0.6247792899247548,
      "grad_norm": 0.9679365158081055,
      "learning_rate": 1.524135271620317e-05,
      "loss": 1.7179,
      "step": 17250
    },
    {
      "epoch": 0.6265902443883049,
      "grad_norm": 0.8675088286399841,
      "learning_rate": 1.4701315480056164e-05,
      "loss": 1.7191,
      "step": 17300
    },
    {
      "epoch": 0.6284011988518549,
      "grad_norm": 0.8750124573707581,
      "learning_rate": 1.4170525729272187e-05,
      "loss": 1.7395,
      "step": 17350
    },
    {
      "epoch": 0.6302121533154049,
      "grad_norm": 0.8760315179824829,
      "learning_rate": 1.3649019742625623e-05,
      "loss": 1.7284,
      "step": 17400
    },
    {
      "epoch": 0.6320231077789549,
      "grad_norm": 0.8750995993614197,
      "learning_rate": 1.3136833164357929e-05,
      "loss": 1.7158,
      "step": 17450
    },
    {
      "epoch": 0.6338340622425049,
      "grad_norm": 0.8723594546318054,
      "learning_rate": 1.2634001001741373e-05,
      "loss": 1.7119,
      "step": 17500
    },
    {
      "epoch": 0.6356450167060549,
      "grad_norm": 0.8465452790260315,
      "learning_rate": 1.2140557622686336e-05,
      "loss": 1.7297,
      "step": 17550
    },
    {
      "epoch": 0.637455971169605,
      "grad_norm": 0.9385716915130615,
      "learning_rate": 1.1656536753392287e-05,
      "loss": 1.7265,
      "step": 17600
    },
    {
      "epoch": 0.6392669256331549,
      "grad_norm": 0.8460535407066345,
      "learning_rate": 1.1181971476042733e-05,
      "loss": 1.7372,
      "step": 17650
    },
    {
      "epoch": 0.641077880096705,
      "grad_norm": 0.9122745990753174,
      "learning_rate": 1.0716894226543953e-05,
      "loss": 1.7483,
      "step": 17700
    },
    {
      "epoch": 0.642888834560255,
      "grad_norm": 0.8963084816932678,
      "learning_rate": 1.0261336792308167e-05,
      "loss": 1.718,
      "step": 17750
    },
    {
      "epoch": 0.644699789023805,
      "grad_norm": 0.9131792187690735,
      "learning_rate": 9.815330310080887e-06,
      "loss": 1.7368,
      "step": 17800
    },
    {
      "epoch": 0.646510743487355,
      "grad_norm": 0.8900518417358398,
      "learning_rate": 9.378905263812697e-06,
      "loss": 1.7319,
      "step": 17850
    },
    {
      "epoch": 0.648321697950905,
      "grad_norm": 0.9023259282112122,
      "learning_rate": 8.952091482575824e-06,
      "loss": 1.7311,
      "step": 17900
    },
    {
      "epoch": 0.6501326524144551,
      "grad_norm": 0.8914921283721924,
      "learning_rate": 8.53491813852521e-06,
      "loss": 1.7361,
      "step": 17950
    },
    {
      "epoch": 0.651943606878005,
      "grad_norm": 0.8964372277259827,
      "learning_rate": 8.127413744904804e-06,
      "loss": 1.7329,
      "step": 18000
    },
    {
      "epoch": 0.651943606878005,
      "eval_loss": 1.7285653352737427,
      "eval_runtime": 70.9767,
      "eval_samples_per_second": 125.379,
      "eval_steps_per_second": 15.681,
      "step": 18000
    },
    {
      "epoch": 0.6537545613415551,
      "grad_norm": 0.8982524275779724,
      "learning_rate": 7.72960615409859e-06,
      "loss": 1.7311,
      "step": 18050
    },
    {
      "epoch": 0.655565515805105,
      "grad_norm": 0.8586708903312683,
      "learning_rate": 7.34152255572697e-06,
      "loss": 1.7198,
      "step": 18100
    },
    {
      "epoch": 0.6573764702686551,
      "grad_norm": 0.8519139885902405,
      "learning_rate": 6.963189474788378e-06,
      "loss": 1.7138,
      "step": 18150
    },
    {
      "epoch": 0.6591874247322052,
      "grad_norm": 0.8693162798881531,
      "learning_rate": 6.594632769846353e-06,
      "loss": 1.7069,
      "step": 18200
    },
    {
      "epoch": 0.6609983791957551,
      "grad_norm": 0.8809148073196411,
      "learning_rate": 6.235877631262093e-06,
      "loss": 1.7233,
      "step": 18250
    },
    {
      "epoch": 0.6628093336593052,
      "grad_norm": 0.881347119808197,
      "learning_rate": 5.886948579472778e-06,
      "loss": 1.7255,
      "step": 18300
    },
    {
      "epoch": 0.6646202881228551,
      "grad_norm": 0.8718705177307129,
      "learning_rate": 5.547869463315597e-06,
      "loss": 1.7177,
      "step": 18350
    },
    {
      "epoch": 0.6664312425864052,
      "grad_norm": 0.8670254349708557,
      "learning_rate": 5.218663458397715e-06,
      "loss": 1.7096,
      "step": 18400
    },
    {
      "epoch": 0.6682421970499551,
      "grad_norm": 0.9031693339347839,
      "learning_rate": 4.899353065512262e-06,
      "loss": 1.7272,
      "step": 18450
    },
    {
      "epoch": 0.6700531515135052,
      "grad_norm": 0.8622111678123474,
      "learning_rate": 4.589960109100444e-06,
      "loss": 1.7202,
      "step": 18500
    },
    {
      "epoch": 0.6718641059770553,
      "grad_norm": 0.9192880392074585,
      "learning_rate": 4.290505735759864e-06,
      "loss": 1.7186,
      "step": 18550
    },
    {
      "epoch": 0.6736750604406052,
      "grad_norm": 0.8716537952423096,
      "learning_rate": 4.001010412799138e-06,
      "loss": 1.7212,
      "step": 18600
    },
    {
      "epoch": 0.6754860149041553,
      "grad_norm": 0.8678475618362427,
      "learning_rate": 3.721493926839042e-06,
      "loss": 1.7058,
      "step": 18650
    },
    {
      "epoch": 0.6772969693677052,
      "grad_norm": 0.8630937337875366,
      "learning_rate": 3.451975382460109e-06,
      "loss": 1.7226,
      "step": 18700
    },
    {
      "epoch": 0.6791079238312553,
      "grad_norm": 0.8803614377975464,
      "learning_rate": 3.192473200896828e-06,
      "loss": 1.7042,
      "step": 18750
    },
    {
      "epoch": 0.6809188782948052,
      "grad_norm": 0.8662247061729431,
      "learning_rate": 2.9430051187785962e-06,
      "loss": 1.715,
      "step": 18800
    },
    {
      "epoch": 0.6827298327583553,
      "grad_norm": 0.8980440497398376,
      "learning_rate": 2.7035881869174603e-06,
      "loss": 1.7265,
      "step": 18850
    },
    {
      "epoch": 0.6845407872219053,
      "grad_norm": 0.8566074967384338,
      "learning_rate": 2.4742387691426445e-06,
      "loss": 1.7169,
      "step": 18900
    },
    {
      "epoch": 0.6863517416854553,
      "grad_norm": 0.8601093292236328,
      "learning_rate": 2.2549725411822483e-06,
      "loss": 1.7266,
      "step": 18950
    },
    {
      "epoch": 0.6881626961490054,
      "grad_norm": 0.9056572914123535,
      "learning_rate": 2.0458044895916513e-06,
      "loss": 1.7167,
      "step": 19000
    },
    {
      "epoch": 0.6881626961490054,
      "eval_loss": 1.7263145446777344,
      "eval_runtime": 71.0987,
      "eval_samples_per_second": 125.164,
      "eval_steps_per_second": 15.654,
      "step": 19000
    },
    {
      "epoch": 0.6899736506125553,
      "grad_norm": 0.8750390410423279,
      "learning_rate": 1.8467489107293509e-06,
      "loss": 1.7176,
      "step": 19050
    },
    {
      "epoch": 0.6917846050761054,
      "grad_norm": 0.8863867521286011,
      "learning_rate": 1.6578194097797258e-06,
      "loss": 1.7091,
      "step": 19100
    },
    {
      "epoch": 0.6935955595396553,
      "grad_norm": 0.8720900416374207,
      "learning_rate": 1.4790288998232314e-06,
      "loss": 1.7133,
      "step": 19150
    },
    {
      "epoch": 0.6954065140032054,
      "grad_norm": 0.8709716796875,
      "learning_rate": 1.3103896009537207e-06,
      "loss": 1.7142,
      "step": 19200
    },
    {
      "epoch": 0.6972174684667554,
      "grad_norm": 0.85850989818573,
      "learning_rate": 1.1519130394432474e-06,
      "loss": 1.7126,
      "step": 19250
    },
    {
      "epoch": 0.6990284229303054,
      "grad_norm": 0.8887191414833069,
      "learning_rate": 1.0036100469542786e-06,
      "loss": 1.7149,
      "step": 19300
    },
    {
      "epoch": 0.7008393773938554,
      "grad_norm": 0.8532807230949402,
      "learning_rate": 8.654907597993532e-07,
      "loss": 1.721,
      "step": 19350
    },
    {
      "epoch": 0.7026503318574054,
      "grad_norm": 0.8430909514427185,
      "learning_rate": 7.375646182482875e-07,
      "loss": 1.7125,
      "step": 19400
    },
    {
      "epoch": 0.7044612863209555,
      "grad_norm": 0.9075100421905518,
      "learning_rate": 6.198403658829232e-07,
      "loss": 1.7069,
      "step": 19450
    },
    {
      "epoch": 0.7062722407845055,
      "grad_norm": 0.9222745299339294,
      "learning_rate": 5.123260489995229e-07,
      "loss": 1.7163,
      "step": 19500
    },
    {
      "epoch": 0.7080831952480555,
      "grad_norm": 0.9021022915840149,
      "learning_rate": 4.1502901605882655e-07,
      "loss": 1.7308,
      "step": 19550
    },
    {
      "epoch": 0.7098941497116055,
      "grad_norm": 0.8747000694274902,
      "learning_rate": 3.2795591718381975e-07,
      "loss": 1.7196,
      "step": 19600
    },
    {
      "epoch": 0.7117051041751555,
      "grad_norm": 0.9012765288352966,
      "learning_rate": 2.5111270370511415e-07,
      "loss": 1.7189,
      "step": 19650
    },
    {
      "epoch": 0.7135160586387055,
      "grad_norm": 0.8706731796264648,
      "learning_rate": 1.8450462775428942e-07,
      "loss": 1.7083,
      "step": 19700
    },
    {
      "epoch": 0.7153270131022555,
      "grad_norm": 0.8779574036598206,
      "learning_rate": 1.2813624190484705e-07,
      "loss": 1.7201,
      "step": 19750
    },
    {
      "epoch": 0.7171379675658056,
      "grad_norm": 0.8768463730812073,
      "learning_rate": 8.201139886109264e-08,
      "loss": 1.7431,
      "step": 19800
    },
    {
      "epoch": 0.7189489220293556,
      "grad_norm": 0.8755491971969604,
      "learning_rate": 4.613325119479649e-08,
      "loss": 1.714,
      "step": 19850
    },
    {
      "epoch": 0.7207598764929056,
      "grad_norm": 0.8661019206047058,
      "learning_rate": 2.0504251129649374e-08,
      "loss": 1.7407,
      "step": 19900
    },
    {
      "epoch": 0.7225708309564556,
      "grad_norm": 0.8537237644195557,
      "learning_rate": 5.1261503738131425e-09,
      "loss": 1.7214,
      "step": 19950
    },
    {
      "epoch": 0.7243817854200056,
      "grad_norm": 0.8425238132476807,
      "learning_rate": 0.0,
      "loss": 1.7156,
      "step": 20000
    },
    {
      "epoch": 0.7243817854200056,
      "eval_loss": 1.725817322731018,
      "eval_runtime": 73.85,
      "eval_samples_per_second": 120.501,
      "eval_steps_per_second": 15.071,
      "step": 20000
    }
  ],
  "logging_steps": 50,
  "max_steps": 20000,
  "num_input_tokens_seen": 0,
  "num_train_epochs": 1,
  "save_steps": 1000,
  "stateful_callbacks": {
    "TrainerControl": {
      "args": {
        "should_epoch_stop": false,
        "should_evaluate": false,
        "should_log": false,
        "should_save": true,
        "should_training_stop": true
      },
      "attributes": {}
    }
  },
  "total_flos": 9287541719040000.0,
  "train_batch_size": 4,
  "trial_name": null,
  "trial_params": null
}
